ipinfo_django/__init__.py
ipinfo_django/helpers.py
ipinfo_django/middleware.py
ipinfo_django/ip_selector/__init__.py
ipinfo_django/ip_selector/default.py
ipinfo_django/ip_selector/interface.py
ipinfo_django/ip_selector/remote_client.py
ipinfo_django-2.3.0.dist-info/licenses/LICENSE
ipinfo_django-2.3.0.dist-info/METADATA
ipinfo_django-2.3.0.dist-info/WHEEL
ipinfo_django-2.3.0.dist-info/top_level.txt
ipinfo_django-2.3.0.dist-info/RECORD
