Metadata-Version: 2.4
Name: ipinfo_django
Version: 2.3.0
Summary: Official Django library for IPinfo
Home-page: https://github.com/ipinfo/django
Author: IPinfo
Author-email: support@ipinfo.io
License: Apache License 2.0
License-File: LICENSE
Requires-Dist: django
Requires-Dist: ipinfo>=5.4.0
Dynamic: author
Dynamic: author-email
Dynamic: description
Dynamic: home-page
Dynamic: license
Dynamic: license-file
Dynamic: requires-dist
Dynamic: summary
